{"id":"MJOSZWAI3N6WN","name":"devotional","size":10207441,"btime":1766870127920,"mtime":1766870127932,"ext":"png","tags":[],"folders":["MJLU35QHIWRNX"],"isDeleted":true,"url":"","annotation":"","modificationTime":1766870366780,"height":1536,"width":2752,"palettes":[{"color":[211,208,132],"ratio":55},{"color":[190,233,214],"ratio":16},{"color":[205,185,83],"ratio":9},{"color":[214,229,177],"ratio":9},{"color":[53,51,29],"ratio":2.39},{"color":[169,187,143],"ratio":1.95},{"color":[189,170,107],"ratio":1.7},{"color":[187,176,49],"ratio":1.44},{"color":[133,129,87],"ratio":1.29},{"color":[162,145,89],"ratio":0.48},{"color":[104,94,54],"ratio":0.41}],"deletedTime":1767114341258,"lastModified":1767114341362}